layer/__init__.py
layer/command_line.py
layer/common.py
layer/config.py
layer/contracts.py
layer/layernode.py
layer/provider.py
layer/signer.py
layer_py-0.0.3.dist-info/METADATA
layer_py-0.0.3.dist-info/RECORD
layer_py-0.0.3.dist-info/WHEEL
layer_py-0.0.3.dist-info/entry_points.txt
layer_py-0.0.3.dist-info/top_level.txt
